cortex_builders/__init__.py
cortex_builders/action_builder.py
cortex_builders/builder_factory.py
cortex_builders/connection_builder.py
cortex_builders/dataset_builder.py
cortex_builders/docker_image_builder.py
cortex_builders/exceptions.py
cortex_builders/magics.py
cortex_builders/schema_builder.py
cortex_builders/skill_builder.py
cortex_builders/resources/Dockerfile.daemon.j2
cortex_builders/resources/Dockerfile.func.j2
cortex_builders/resources/Dockerfile.job.j2
cortex_builders/resources/__init__.py
cortex_builders/resources/daemon.py.j2
cortex_builders/resources/func.py.j2
cortex_builders/resources/job.py.j2
cortex_builders/resources/predict_function_sklearn.py.j2
cortex_builders/utils/__init__.py
cortex_builders/utils/docker_utils.py
cortex_builders/utils/python_utils.py
cortex_builders/utils/template_utils.py
test/__init__.py
test/unit/__init__.py
test/unit/ames_test.py
test/unit/connection_save_test.py
test/unit/dataset_test.py
test/unit/dockerutils_test.py
test/unit/fixtures.py
test/unit/namespace_test.py
test/unit/skill_test.py
cortex_python_builders-1.2.1.dist-info/LICENSE
cortex_python_builders-1.2.1.dist-info/METADATA
cortex_python_builders-1.2.1.dist-info/WHEEL
cortex_python_builders-1.2.1.dist-info/top_level.txt
cortex_python_builders-1.2.1.dist-info/RECORD
