Metadata-Version: 2.1
Name: cortex-python-builders
Version: 1.2.1
Summary: Support for programmatic creation of resources in the CognitiveScale Cortex Cognitive Platform
Home-page: https://github.com/CognitiveScale/cortex-python-builders
Author: CognitiveScale
Author-email: info@cognitivescale.com
License: Apache License Version 2.0
Platform: linux
Platform: osx
Classifier: Operating System :: MacOS :: MacOS X
Classifier: Operating System :: POSIX
Classifier: Programming Language :: Python :: 3.6
Requires-Dist: cortex-python (>=1.4.0)
Requires-Dist: cuid (<1,>=0.3)
Requires-Dist: dill (>=0.2.8.2)
Requires-Dist: pyjwt (<2,>=1.6.1)
Requires-Dist: jinja2
Requires-Dist: docker (>=3.7.2)
Requires-Dist: tenacity (>=5.0.2)
Requires-Dist: more-itertools (>=4.3.0)
Requires-Dist: dataclasses (>=0.6) ; python_version == "3.6"
